ease_grid/__init__.py
ease_grid/_version.py
ease_grid/ease2_grid.py
ease_grid-0.3.dist-info/licenses/AUTHORS.rst
ease_grid-0.3.dist-info/licenses/LICENSE.txt
ease_grid-0.3.dist-info/METADATA
ease_grid-0.3.dist-info/WHEEL
ease_grid-0.3.dist-info/top_level.txt
ease_grid-0.3.dist-info/RECORD
