Metadata-Version: 2.4
Name: ease_grid
Version: 0.3
Summary: EASE grid generation
Author-email: TU Wien <remote.sensing@geo.tuwien.ac.at>
License: MIT
Project-URL: Documentation, https://ease-grid.readthedocs.io/en/latest/?badge=latest
Project-URL: Homepage, https://ease-grid.readthedocs.io/en/latest/?badge=latest
Classifier: Development Status :: 4 - Beta
Classifier: Programming Language :: Python
Requires-Python: >=3.9
License-File: LICENSE.txt
License-File: AUTHORS.rst
Requires-Dist: numpy
Requires-Dist: pyproj
Provides-Extra: testing
Requires-Dist: pytest; extra == "testing"
Requires-Dist: pytest-cov; extra == "testing"
Dynamic: license-file
